MANIFEST.in
README.rst
setup.py
Ferdowsi_Cal/__init__.py
Ferdowsi_Cal/admin.py
Ferdowsi_Cal/apps.py
Ferdowsi_Cal/models.py
Ferdowsi_Cal/tests.py
Ferdowsi_Cal/urls.py
Ferdowsi_Cal/views.py
Ferdowsi_Cal/migrations/0001_initial.py
Ferdowsi_Cal/migrations/__init__.py
Ferdowsi_Cal/static/Ferdowsi_Cal/css/B-Nazanin_5370.ttf
Ferdowsi_Cal/static/Ferdowsi_Cal/css/gregorian_style.css
Ferdowsi_Cal/static/Ferdowsi_Cal/css/persian_style.css
Ferdowsi_Cal/static/Ferdowsi_Cal/js/diagram.js
Ferdowsi_Cal/static/Ferdowsi_Cal/js/gchart.js
Ferdowsi_Cal/static/Ferdowsi_Cal/js/gregorian_script.js
Ferdowsi_Cal/static/Ferdowsi_Cal/js/gregorian_script_user.js
Ferdowsi_Cal/static/Ferdowsi_Cal/js/my_jquery.js
Ferdowsi_Cal/static/Ferdowsi_Cal/js/persian_script.js
Ferdowsi_Cal/static/Ferdowsi_Cal/js/persian_script_user.js
Ferdowsi_Cal/templates/Ferdowsi_Cal/diagram.html
Ferdowsi_Cal/templates/Ferdowsi_Cal/gregorian_calendar.html
Ferdowsi_Cal/templates/Ferdowsi_Cal/gregorian_calendar_user.html
Ferdowsi_Cal/templates/Ferdowsi_Cal/persian_calendar.html
Ferdowsi_Cal/templates/Ferdowsi_Cal/persian_calendar_user.html
Ferdowsi_Cal/templatetags/__init__.py
Ferdowsi_Cal/templatetags/my_tags.py
django_ferdowsiCalendar.egg-info/PKG-INFO
django_ferdowsiCalendar.egg-info/SOURCES.txt
django_ferdowsiCalendar.egg-info/dependency_links.txt
django_ferdowsiCalendar.egg-info/top_level.txt